invocation_tree/__init__.py
invocation_tree/regex_set.py
invocation_tree-0.0.35.dist-info/licenses/LICENSE.txt
invocation_tree-0.0.35.dist-info/METADATA
invocation_tree-0.0.35.dist-info/WHEEL
invocation_tree-0.0.35.dist-info/top_level.txt
invocation_tree-0.0.35.dist-info/RECORD
