Metadata-Version: 2.4
Name: invocation_tree
Version: 0.0.35
Summary: Generates an invocation tree of functions calls.
Author-email: Bas Terwijn <bterwijn@gmail.com>
License-Expression: BSD-2-Clause
Project-URL: Homepage, https://github.com/bterwijn/invocation_tree
Project-URL: Repository, https://github.com/bterwijn/invocation_tree.git
Classifier: Development Status :: 4 - Beta
Classifier: Intended Audience :: Education
Classifier: Intended Audience :: Developers
Classifier: Programming Language :: Python :: 3
Classifier: Topic :: Education
Classifier: Topic :: Software Development :: Debuggers
Requires-Python: >=3.7
License-File: LICENSE.txt
Requires-Dist: graphviz
Dynamic: license-file
